example_package_shinumerde/__init__.py
example_package_shinumerde/prog.py
example_package_shinumerde-2024.2.9.dist-info/METADATA
example_package_shinumerde-2024.2.9.dist-info/WHEEL
example_package_shinumerde-2024.2.9.dist-info/licenses/LICENSE
example_package_shinumerde-2024.2.9.dist-info/RECORD
